cli/__init__.py
cli/cli.py
co_connect_pseudonymise-0.3.dist-info/METADATA
co_connect_pseudonymise-0.3.dist-info/WHEEL
co_connect_pseudonymise-0.3.dist-info/entry_points.txt
co_connect_pseudonymise-0.3.dist-info/top_level.txt
co_connect_pseudonymise-0.3.dist-info/RECORD
