Metadata-Version: 2.1
Name: co-connect-pseudonymise
Version: 0.3
Summary: CommandLine Interface for pseudonymising data.
Home-page: https://github.com/CO-CONNECT/Pseudonymisation
Author: CO-CONNECT
Author-email: CO-CONNECT@dundee.ac.uk
License: UNKNOWN
Platform: UNKNOWN
Classifier: Programming Language :: Python :: 3
Classifier: License :: OSI Approved :: MIT License
Classifier: Operating System :: OS Independent
Requires-Python: >=3.6
Requires-Dist: pandas
Requires-Dist: click
Requires-Dist: loguru
